aspectify/__init__.py
aspectify/_modidx.py
aspectify/aop.py
aspectify/examples.py
aspectify/examples2.py
aspectify-1.0.0.dist-info/LICENSE
aspectify-1.0.0.dist-info/METADATA
aspectify-1.0.0.dist-info/WHEEL
aspectify-1.0.0.dist-info/entry_points.txt
aspectify-1.0.0.dist-info/top_level.txt
aspectify-1.0.0.dist-info/RECORD
