Metadata-Version: 2.1
Name: aspectify
Version: 1.0.0
Summary: Apply Aspect Oriented Programming to your Python code
Home-page: https://github.com/ruescog/aspectify
Author: ruescog
Author-email: ruescog@unirioja.es
License: Apache Software License 2.0
Keywords: nbdev jupyter notebook python
Platform: UNKNOWN
Classifier: Development Status :: 4 - Beta
Classifier: Intended Audience :: Developers
Classifier: Natural Language :: English
Classifier: Programming Language :: Python :: 3.7
Classifier: Programming Language :: Python :: 3.8
Classifier: Programming Language :: Python :: 3.9
Classifier: Programming Language :: Python :: 3.10
Classifier: License :: OSI Approved :: Apache Software License
Requires-Python: >=3.7
Provides-Extra: dev
